mach_client/__init__.py
mach_client/config.py
mach_client/log.py
mach_client/account/__init__.py
mach_client/account/account.py
mach_client/account/account_manager.py
mach_client/account/ethereum.py
mach_client/account/hdwallet.py
mach_client/account/solana.py
mach_client/account/tron.py
mach_client/asset/__init__.py
mach_client/asset/asset.py
mach_client/asset/ethereum.py
mach_client/asset/solana.py
mach_client/asset/token.py
mach_client/asset/tron.py
mach_client/chain/__init__.py
mach_client/chain/chain.py
mach_client/chain/constants.py
mach_client/chain/ethereum.py
mach_client/chain/solana.py
mach_client/chain/tron.py
mach_client/chain_client/__init__.py
mach_client/chain_client/chain_client.py
mach_client/chain_client/ethereum.py
mach_client/chain_client/solana.py
mach_client/chain_client/tron.py
mach_client/client/__init__.py
mach_client/client/event.py
mach_client/client/risk_manager.py
mach_client/client/utility.py
mach_client/client/asset_server/__init__.py
mach_client/client/asset_server/types.py
mach_client/client/cctp/__init__.py
mach_client/client/cctp/ethereum.py
mach_client/client/cctp/solana/__init__.py
mach_client/client/cctp/solana/anchor/__init__.py
mach_client/client/cctp/solana/anchor/program_id.py
mach_client/client/cctp/solana/anchor/accounts/__init__.py
mach_client/client/cctp/solana/anchor/accounts/local_token.py
mach_client/client/cctp/solana/anchor/accounts/remote_token_messenger.py
mach_client/client/cctp/solana/anchor/accounts/token_messenger.py
mach_client/client/cctp/solana/anchor/accounts/token_minter.py
mach_client/client/cctp/solana/anchor/accounts/token_pair.py
mach_client/client/cctp/solana/anchor/errors/__init__.py
mach_client/client/cctp/solana/anchor/errors/anchor.py
mach_client/client/cctp/solana/anchor/errors/custom.py
mach_client/client/cctp/solana/anchor/instructions/__init__.py
mach_client/client/cctp/solana/anchor/instructions/accept_ownership.py
mach_client/client/cctp/solana/anchor/instructions/add_local_token.py
mach_client-0.1.86.dist-info/METADATA
mach_client-0.1.86.dist-info/WHEEL
mach_client-0.1.86.dist-info/RECORD
